soul/__init__.py
soul/words.py
soul/decorators/__init__.py
soul/decorators/decorators.py
soul/files/__init__.py
soul/files/files.py
soul/functional/__init__.py
soul/functional/functional.py
soul/trips/__init__.py
soul/trips/graph.py
thesoulshell-0.0.3.dist-info/METADATA
thesoulshell-0.0.3.dist-info/WHEEL
thesoulshell-0.0.3.dist-info/top_level.txt
thesoulshell-0.0.3.dist-info/RECORD
