Metadata-Version: 2.1
Name: thesoulshell
Version: 0.0.3
Summary: add a little soul to your python
Home-page: https://github.com/mrmechko/soul
Author: Rik Bose
Author-email: rbose@cs.rochester.edu
License: UNKNOWN
Platform: UNKNOWN
Classifier: Programming Language :: Python :: 3
Classifier: License :: OSI Approved :: GNU General Public License v2 or later (GPLv2+)
Classifier: Operating System :: OS Independent
